odoo/addons/usability_webhooks/README.rst
odoo/addons/usability_webhooks/__init__.py
odoo/addons/usability_webhooks/__manifest__.py
odoo/addons/usability_webhooks/controllers/__init__.py
odoo/addons/usability_webhooks/controllers/main.py
odoo/addons/usability_webhooks/controllers/utils.py
odoo/addons/usability_webhooks/data/config_parameter.xml
odoo/addons/usability_webhooks/data/ir_cron.xml
odoo/addons/usability_webhooks/i18n/usability_webhooks.pot
odoo/addons/usability_webhooks/models/__init__.py
odoo/addons/usability_webhooks/models/api_log.py
odoo/addons/usability_webhooks/readme/CONTRIBUTORS.rst
odoo/addons/usability_webhooks/readme/DESCRIPTION.rst
odoo/addons/usability_webhooks/readme/USAGE.rst
odoo/addons/usability_webhooks/security/ir.model.access.csv
odoo/addons/usability_webhooks/static/description/icon.png
odoo/addons/usability_webhooks/static/description/index.html
odoo/addons/usability_webhooks/tests/__init__.py
odoo/addons/usability_webhooks/tests/api_log_tester.py
odoo/addons/usability_webhooks/tests/test_webhook_utils.py
odoo/addons/usability_webhooks/views/api_log.xml
odoo_addon_usability_webhooks-18.0.1.0.1.dist-info/METADATA
odoo_addon_usability_webhooks-18.0.1.0.1.dist-info/WHEEL
odoo_addon_usability_webhooks-18.0.1.0.1.dist-info/top_level.txt
odoo_addon_usability_webhooks-18.0.1.0.1.dist-info/RECORD
